pyoneall
