Metadata-Version: 1.1
Name: pyoneall
Version: 0.2.2
Summary: OneAll API wrapper (http://www.oneall.com). Provides unified API for 30+ social networks
Home-page: http://www.leandigo.com/
Author: Ekevoo
Author-email: ekevoo@gmail.com
License: MIT License, see LICENSE file
Platform: UNKNOWN
Classifier: Development Status :: 5 - Production/Stable
Classifier: Intended Audience :: Developers
Classifier: License :: OSI Approved :: MIT License
Classifier: Operating System :: OS Independent
Classifier: Programming Language :: Python
Classifier: Programming Language :: Python :: 2
Classifier: Programming Language :: Python :: 2.7
Classifier: Programming Language :: Python :: 3
Classifier: Programming Language :: Python :: 3.3
Classifier: Programming Language :: Python :: 3.4
Classifier: Programming Language :: Python :: 3.5
Classifier: Topic :: Internet :: WWW/HTTP :: Session
Classifier: Topic :: System :: Systems Administration :: Authentication/Directory
